pylpsd/__init__.py
pylpsd/_version.py
pylpsd/lpsd.py
pylpsd-0.1.4.dist-info/LICENSE
pylpsd-0.1.4.dist-info/METADATA
pylpsd-0.1.4.dist-info/WHEEL
pylpsd-0.1.4.dist-info/top_level.txt
pylpsd-0.1.4.dist-info/RECORD
