Metadata-Version: 2.1
Name: pylpsd
Version: 0.1.4
Summary: Method for calulating power spectrum on logarithmic frequency axis.
Home-page: https://github.com/bleykauf/py-lpsd
Author: Rudolf W. Byker
Maintainer: Bastian Leykauf
Maintainer-email: leykauf@physik.hu-berlin.de
License: UNKNOWN
Platform: UNKNOWN
Classifier: Programming Language :: Python :: 3
Classifier: Operating System :: OS Independent
Classifier: Intended Audience :: Science/Research
Requires-Python: >=3.5
License-File: LICENSE
Requires-Dist: numpy
Requires-Dist: scipy
